tapioca_circleci/__init__.py
tapioca_circleci/resource_mapping.py
tapioca_circleci/tapioca_circleci.py
tapioca_circleci-0.0.1.dist-info/DESCRIPTION.rst
tapioca_circleci-0.0.1.dist-info/METADATA
tapioca_circleci-0.0.1.dist-info/RECORD
tapioca_circleci-0.0.1.dist-info/WHEEL
tapioca_circleci-0.0.1.dist-info/metadata.json
tapioca_circleci-0.0.1.dist-info/top_level.txt
