Metadata-Version: 2.0
Name: tapioca-circleci
Version: 0.0.1
Summary: CircleCI API wrapper using tapioca
Home-page: https://github.com/georgeyk/tapioca-circleci/
Author: George Y. Kussumoto
Author-email: contato@georgeyk.com.br
License: MIT
Download-URL: https://github.com/georgeyk/tapioca-circleci/releases/
Keywords: circleci,api,wrapper
Platform: UNKNOWN
Classifier: Development Status :: 4 - Beta
Classifier: Environment :: Console
Classifier: Intended Audience :: Developers
Classifier: License :: OSI Approved :: MIT License
Classifier: Natural Language :: English
Classifier: Operating System :: OS Independent
Classifier: Programming Language :: Python :: 3 :: Only
Classifier: Programming Language :: Python :: 3.5
Requires-Dist: tapioca-wrapper (<2)
